mm/__init__.py
mm/app.py
mm/config.py
mm/data.py
mm/utils.py
mm/gui/__init__.py
mm/gui/default.ui
mm/gui/draggable.py
mm/gui/popup_menu.py
mm/gui/settings.py
mm/gui/win.py
mm/indicator/__init__.py
mm/indicator/chart.py
mm/indicator/simple.py
mm/sensor/__init__.py
mm/sensor/simple.py
mini_monitor-0.3.6.dist-info/METADATA
mini_monitor-0.3.6.dist-info/WHEEL
mini_monitor-0.3.6.dist-info/entry_points.txt
mini_monitor-0.3.6.dist-info/top_level.txt
mini_monitor-0.3.6.dist-info/RECORD
